[
    {
        "judul": "Satu Orang Meninggal Akibat DBD, Petugas Gabungan di Madiun Lakukan Pengasapan",
        "kategori": "Visual",
        "waktu_publish": "24 detik yang lalu",
        "waktu_scraping": "2024-04-15 20:30:19",
        "url": "https://visual.republika.co.id/berita/sbzitf375/satu-orang-meninggal-akibat-dbd-petugas-gabungan-di-madiun-lakukan-pengasapan"
    },
    {
        "judul": "Jerman Minta Iran tak Meningkatkan Ketegangan",
        "kategori": "Internasional",
        "waktu_publish": "3 menit yang lalu",
        "waktu_scraping": "2024-04-15 20:30:19",
        "url": "https://internasional.republika.co.id/berita/sbzk1x423/jerman-minta-iran-tak-meningkatkan-ketegangan"
    },
    {
        "judul": "Golkar Undang PPP Halal Bihalal: Kenang Koalisi Indonesia Bersatu",
        "kategori": "News",
        "waktu_publish": "4 menit yang lalu",
        "waktu_scraping": "2024-04-15 20:30:19",
        "url": "https://news.republika.co.id/berita/sbzk0k484/golkar-undang-ppp-halal-bihalal-kenang-koalisi-indonesia-bersatu"
    },
    {
        "judul": "Bentrok TNI-Polri Kembali Terjadi, Dewan Ingatkan Bahaya Ego Sektoral",
        "kategori": "News",
        "waktu_publish": "8 menit yang lalu",
        "waktu_scraping": "2024-04-15 20:30:19",
        "url": "https://news.republika.co.id/berita/sbzjtp320/bentrok-tnipolri-kembali-terjadi-dewan-ingatkan-bahaya-ego-sektoral"
    },
    {
        "judul": "Aktris Kim Ji-won Catat Rekor Langka 'Big 4' Berkat Drama 'Queen of Tears', Apa Itu?",
        "kategori": "Ameera",
        "waktu_publish": "8 menit yang lalu",
        "waktu_scraping": "2024-04-15 20:30:19",
        "url": "https://ameera.republika.co.id/berita/sbzjsy425/aktris-kim-jiwon-catat-rekor-langka-big-4-berkat-drama-queen-of-tears-apa-itu"
    },
    {
        "judul": "Bus ALS Terbalik di Jalur One Way Malalak Kabupaten Agam",
        "kategori": "Ramadhan",
        "waktu_publish": "9 menit yang lalu",
        "waktu_scraping": "2024-04-15 20:30:19",
        "url": "https://ramadhan.republika.co.id/berita/sbzjry423/bus-als-terbalik-di-jalur-one-way-malalak-kabupaten-agam"
    },
    {
        "judul": "Kecelakaan Beruntun di Tol Cipali, Satu Orang Meninggal Dunia",
        "kategori": "Ramadhan",
        "waktu_publish": "15 menit yang lalu",
        "waktu_scraping": "2024-04-15 20:30:19",
        "url": "https://ramadhan.republika.co.id/berita/sbzjhf423/kecelakaan-beruntun-di-tol-cipali-satu-orang-meninggal-dunia"
    },
    {
        "judul": "Jasamarga: Senin Masih Terjadi Arus Balik di Tol Padaleunyi-Cipularang",
        "kategori": "News",
        "waktu_publish": "16 menit yang lalu",
        "waktu_scraping": "2024-04-15 20:30:19",
        "url": "https://news.republika.co.id/berita/sbzjgs502/jasamarga-senin-masih-terjadi-arus-balik-di-tol-padaleunyicipularang"
    },
    {
        "judul": "Menemukan 'Inner Peace' di Tengah Karut Marut Zaman",
        "kategori": "Retizen",
        "waktu_publish": "16 menit yang lalu",
        "waktu_scraping": "2024-04-15 20:30:19",
        "url": "https://retizen.republika.co.id/posts/301466/menemukan-inner-peace-di-tengah-karut-marut-zaman"
    },
    {
        "judul": "Timnas Indonesia U-23 Bertekad Curi Poin dari Tuan Rumah Qatar",
        "kategori": "Sport",
        "waktu_publish": "17 menit yang lalu",
        "waktu_scraping": "2024-04-15 20:30:19",
        "url": "https://sport.republika.co.id/berita/sbzje1257/timnas-indonesia-u23-bertekad-curi-poin-dari-tuan-rumah-qatar"
    },
    {
        "judul": "Mengapa Islam Melarang Permusuhan dan Perbuatan Zalim Antarsesama?",
        "kategori": "Khazanah",
        "waktu_publish": "17 menit yang lalu",
        "waktu_scraping": "2024-04-15 20:30:19",
        "url": "https://khazanah.republika.co.id/berita/sbzjdx320/mengapa-islam-melarang-permusuhan-dan-perbuatan-zalim-antarsesama"
    },
    {
        "judul": "Jadilah Orang yang Mendukung, Bukan Pengamat",
        "kategori": "Retizen",
        "waktu_publish": "18 menit yang lalu",
        "waktu_scraping": "2024-04-15 20:30:19",
        "url": "https://retizen.republika.co.id/posts/301465/jadilah-orang-yang-mendukung-bukan-pengamat"
    },
    {
        "judul": "Nasdem Terbuka Atas Peluang Usung Anies di Pilgub Jakarta 2024",
        "kategori": "News",
        "waktu_publish": "19 menit yang lalu",
        "waktu_scraping": "2024-04-15 20:30:19",
        "url": "https://news.republika.co.id/berita/sbzjbe409/nasdem-terbuka-atas-peluang-usung-anies-di-pilgub-jakarta-2024"
    },
    {
        "judul": "Anies dan Muhaimin Belum Bertemu Surya Paloh di Momen Idulfitri\u00a0Tahun Ini",
        "kategori": "News",
        "waktu_publish": "22 menit yang lalu",
        "waktu_scraping": "2024-04-15 20:30:19",
        "url": "https://news.republika.co.id/berita/sbzj5i409/anies-dan-muhaimin-belum-bertemu-surya-paloh-di-momen-idulfitritahun-ini"
    },
    {
        "judul": "15 Ribu Wisatawan Berkunjung ke Raya Cibodas Selama Libur Lebaran",
        "kategori": "Ramadhan",
        "waktu_publish": "24 menit yang lalu",
        "waktu_scraping": "2024-04-15 20:30:19",
        "url": "https://ramadhan.republika.co.id/berita/sbzj1x425/15-ribu-wisatawan-berkunjung-ke-raya-cibodas-selama-libur-lebaran"
    },
    {
        "judul": "Antisipasi Dampak Ekonomi Serangan Iran ke Israel, Airlangga Ambil Langkah Ini",
        "kategori": "Ekonomi",
        "waktu_publish": "27 menit yang lalu",
        "waktu_scraping": "2024-04-15 20:30:19",
        "url": "https://ekonomi.republika.co.id/berita/sbziy0502/antisipasi-dampak-ekonomi-serangan-iran-ke-israel-airlangga-ambil-langkah-ini"
    },
    {
        "judul": "Puluhan Ribu Wisatawan Kunjungi Dieng Saat Libur Lebaran",
        "kategori": "Rejogja",
        "waktu_publish": "30 menit yang lalu",
        "waktu_scraping": "2024-04-15 20:30:19",
        "url": "https://rejogja.republika.co.id/berita/sbzit7432/puluhan-ribu-wisatawan-kunjungi-dieng-saat-libur-lebaran"
    },
    {
        "judul": "Dipadati Kendaraan Arus Balik Pemudik, Simpang Ajibarang Macet 7 Km",
        "kategori": "Visual",
        "waktu_publish": "34 menit yang lalu",
        "waktu_scraping": "2024-04-15 20:30:19",
        "url": "https://visual.republika.co.id/berita/sbzild375/dipadati-kendaraan-arus-balik-pemudik-simpang-ajibarang-macet-7-km"
    },
    {
        "judul": "30 Ribu Wisatawan Serbu Bianglala Terbesar Sumatra di Palembang",
        "kategori": "Ramadhan",
        "waktu_publish": "39 menit yang lalu",
        "waktu_scraping": "2024-04-15 20:30:19",
        "url": "https://ramadhan.republika.co.id/berita/sbzidk366/30-ribu-wisatawan-serbu-bianglala-terbesar-sumatra-di-palembang"
    },
    {
        "judul": "Polisi Pastikan tak Ada Kemacetan Parah pada Arus Wisata Puncak Bogor",
        "kategori": "Ramadhan",
        "waktu_publish": "40 menit yang lalu",
        "waktu_scraping": "2024-04-15 20:30:19",
        "url": "https://ramadhan.republika.co.id/berita/sbzic8425/polisi-pastikan-tak-ada-kemacetan-parah-pada-arus-wisata-puncak-bogor"
    },
    {
        "judul": "Polda Metro Terima Laporan Asep Adang, Pengendara Fortuner Arogan Berpelat TNI Diusut",
        "kategori": "News",
        "waktu_publish": "42 menit yang lalu",
        "waktu_scraping": "2024-04-15 20:30:19",
        "url": "https://news.republika.co.id/berita/sbzi8v409/polda-metro-terima-laporan-asep-adang-pengendara-fortuner-arogan-berpelat-tni-diusut"
    },
    {
        "judul": "Masih Ada 40 Ribu Kendaraan di Lampung Belum Menyeberang ke Jawa",
        "kategori": "Ramadhan",
        "waktu_publish": "47 menit yang lalu",
        "waktu_scraping": "2024-04-15 20:30:19",
        "url": "https://ramadhan.republika.co.id/berita/sbzi13366/masih-ada-40-ribu-kendaraan-di-lampung-belum-menyeberang-ke-jawa"
    },
    {
        "judul": "Wajib Tahu, Pilihan Olahraga Pasca Lebaran Sebelum Kembali Beraktivitas Dalam Rutinitas",
        "kategori": "Network",
        "waktu_publish": "49 menit yang lalu",
        "waktu_scraping": "2024-04-15 20:30:19",
        "url": "https://topnews62.com/posts/301454/wajib-tahu-pilihan-olahraga-pasca-lebaran-sebelum-kembali-beraktivitas-dalam-rutinitas"
    },
    {
        "judul": "Sistem One Way di Jalur Puncak Diakhiri, Lalin Kembali Normal Dua Arah",
        "kategori": "News",
        "waktu_publish": "53 menit yang lalu",
        "waktu_scraping": "2024-04-15 20:30:19",
        "url": "https://news.republika.co.id/berita/sbzhq1409/sistem-one-way-di-jalur-puncak-diakhiri-lalin-kembali-normal-dua-arah"
    },
    {
        "judul": "Hizbullah Luncurkan Puluhan Roket ke Israel",
        "kategori": "Internasional",
        "waktu_publish": "57 menit yang lalu",
        "waktu_scraping": "2024-04-15 20:30:19",
        "url": "https://internasional.republika.co.id/berita/sbzhjp366/hizbullah-luncurkan-puluhan-roket-ke-israel"
    },
    {
        "judul": "Kapolri Pastikan Semua Pihak Bersinergi Beri Pelayanan Terbaik Arus Balik Lebaran",
        "kategori": "News",
        "waktu_publish": "57 menit yang lalu",
        "waktu_scraping": "2024-04-15 20:30:19",
        "url": "https://news.republika.co.id/berita/sbzhiz423/kapolri-pastikan-semua-pihak-bersinergi-beri-pelayanan-terbaik-arus-balik-lebaran"
    },
    {
        "judul": "Kapolri Prediksi Puncak Arus Balik akan Terjadi pada Senin Malam Ini",
        "kategori": "News",
        "waktu_publish": "58 menit yang lalu",
        "waktu_scraping": "2024-04-15 20:30:19",
        "url": "https://news.republika.co.id/berita/sbzhhk409/kapolri-prediksi-puncak-arus-balik-akan-terjadi-pada-senin-malam-ini"
    },
    {
        "judul": "Arab Saudi Umumkan Tanggal Kedaluwarsa Visa Umroh 15 Dzulqaidah",
        "kategori": "Ihram",
        "waktu_publish": "1 jam yang lalu",
        "waktu_scraping": "2024-04-15 20:30:19",
        "url": "https://ihram.republika.co.id/berita/sbzhb2366/arab-saudi-umumkan-tanggal-kedaluwarsa-visa-umroh-15-dzulqaidah"
    },
    {
        "judul": "Polisi Jelaskan Peran HSA dan Istri Anggota TNI di Kasus Dugaan Pelanggaran UU ITE",
        "kategori": "News",
        "waktu_publish": "1 jam yang lalu",
        "waktu_scraping": "2024-04-15 20:30:19",
        "url": "https://news.republika.co.id/berita/sbzhaa409/polisi-jelaskan-peran-hsa-dan-istri-anggota-tni-di-kasus-dugaan-pelanggaran-uu-ite"
    },
    {
        "judul": "Pemimpin Negara Barat Minta Israel tidak Balas Serangan Iran",
        "kategori": "Internasional",
        "waktu_publish": "1 jam yang lalu",
        "waktu_scraping": "2024-04-15 20:30:19",
        "url": "https://internasional.republika.co.id/berita/sbzh26366/pemimpin-negara-barat-minta-israel-tidak-balas-serangan-iran"
    },
    {
        "judul": "Rumah Pemenangan Prabowo-Gibran Dibobol Maling, Televisi 32 Inci Raib",
        "kategori": "News",
        "waktu_publish": "1 jam yang lalu",
        "waktu_scraping": "2024-04-15 20:30:19",
        "url": "https://news.republika.co.id/berita/sbzh1t320/rumah-pemenangan-prabowogibran-dibobol-maling-televisi-32-inci-raib"
    },
    {
        "judul": "5 Tempat Wisata Gratis di Bandung yang Wajib Dikunjungi!",
        "kategori": "Network",
        "waktu_publish": "1 jam yang lalu",
        "waktu_scraping": "2024-04-15 20:30:19",
        "url": "https://bandung24jam.id/posts/301447/5-tempat-wisata-gratis-di-bandung-yang-wajib-dikunjungi-"
    },
    {
        "judul": "Ketika Aktor Morgan Freeman Coba Kumandangkan Adzan di Masjid Kairo",
        "kategori": "Khazanah",
        "waktu_publish": "1 jam yang lalu",
        "waktu_scraping": "2024-04-15 20:30:19",
        "url": "https://khazanah.republika.co.id/berita/sbzgtz366/ketika-aktor-morgan-freeman-coba-kumandangkan-adzan-di-masjid-kairo"
    },
    {
        "judul": "Puncak Arus Balik, 101.976 Kendaraan Keluar dari DIY",
        "kategori": "Rejogja",
        "waktu_publish": "1 jam yang lalu",
        "waktu_scraping": "2024-04-15 20:30:19",
        "url": "https://rejogja.republika.co.id/berita/sbzgql432/puncak-arus-balik-101976-kendaraan-keluar-dari-diy"
    },
    {
        "judul": "Pemudik Arus Balik dengan Kapal Perang Tiba di Pelabuhan Tanjung Priok",
        "kategori": "Visual",
        "waktu_publish": "1 jam yang lalu",
        "waktu_scraping": "2024-04-15 20:30:19",
        "url": "https://visual.republika.co.id/berita/sbze3h375/pemudik-arus-balik-dengan-kapal-perang-tiba-di-pelabuhan-tanjung-priok"
    },
    {
        "judul": "Tidak Benar Ada Pergantian Seragam Sekolah, Disdik Depok Tegaskan Cuma Ada Tambahan Pakaian Adat",
        "kategori": "Network",
        "waktu_publish": "1 jam yang lalu",
        "waktu_scraping": "2024-04-15 20:30:19",
        "url": "https://ruzka.republika.co.id/nasional/1674542852/tidak-benar-ada-pergantian-seragam-sekolah-disdik-depok-tegaskan-cuma-ada-tambahan-pakaian-adat"
    },
    {
        "judul": "Gempa Bawean, Bayi Lahir di Bawah Tenda Terpal",
        "kategori": "Network",
        "waktu_publish": "1 jam yang lalu",
        "waktu_scraping": "2024-04-15 20:30:19",
        "url": "https://boyanesia.republika.co.id/news/1644542837/gempa-bawean-bayi-lahir-di-bawah-tenda-terpal"
    },
    {
        "judul": "Inter Berpeluang Kunci Scudetto di Depan Suporter 'Musuh Sekota'",
        "kategori": "Sport",
        "waktu_publish": "1 jam yang lalu",
        "waktu_scraping": "2024-04-15 20:30:19",
        "url": "https://sport.republika.co.id/berita/sbzf7a257/inter-berpeluang-kunci-scudetto-di-depan-suporter-musuh-sekota"
    },
    {
        "judul": "Iran Negara Islam dengan Kemajuan Sains Dikagumi Sekaligus Ditakuti Barat, Ini Rahasianya",
        "kategori": "Khazanah",
        "waktu_publish": "1 jam yang lalu",
        "waktu_scraping": "2024-04-15 20:30:19",
        "url": "https://khazanah.republika.co.id/berita/sbzgez320/iran-negara-islam-dengan-kemajuan-sains-dikagumi-sekaligus-ditakuti-barat-ini-rahasianya"
    },
    {
        "judul": "Ini yang tak Boleh Dilakukan Wisatawan Saat Datang ke Festival Sakura di Jepang",
        "kategori": "Ameera",
        "waktu_publish": "1 jam yang lalu",
        "waktu_scraping": "2024-04-15 20:30:19",
        "url": "https://ameera.republika.co.id/berita/sbzgb2425/ini-yang-tak-boleh-dilakukan-wisatawan-saat-datang-ke-festival-sakura-di-jepang"
    },
    {
        "judul": "Bocah Terperosok Celah Peron Stasiun Manggarai, Begini Respons KCI",
        "kategori": "News",
        "waktu_publish": "2 jam yang lalu",
        "waktu_scraping": "2024-04-15 20:30:19",
        "url": "https://news.republika.co.id/berita/sbzfrk484/bocah-terperosok-celah-peron-stasiun-manggarai-begini-respons-kci"
    },
    {
        "judul": "Kebijakan ASN Boleh WFH Setelah Libur Lebaran, Ini Respons Pemprov Jatim",
        "kategori": "Rejogja",
        "waktu_publish": "2 jam yang lalu",
        "waktu_scraping": "2024-04-15 20:30:19",
        "url": "https://rejogja.republika.co.id/berita/sbzfub432/kebijakan-asn-boleh-wfh-setelah-libur-lebaran-ini-respons-pemprov-jatim"
    },
    {
        "judul": "Komentar Ryeowook Super Junior Soal Nyanyi Live Muncul Lagi di Tengah Festival Coachella",
        "kategori": "Ameera",
        "waktu_publish": "2 jam yang lalu",
        "waktu_scraping": "2024-04-15 20:30:19",
        "url": "https://ameera.republika.co.id/berita/sbzft2425/komentar-ryeowook-super-junior-soal-nyanyi-live-muncul-lagi-di-tengah-festival-coachella"
    },
    {
        "judul": "Putra Lionel Messi Cetak Lima Gol untuk Inter Miami",
        "kategori": "Sport",
        "waktu_publish": "2 jam yang lalu",
        "waktu_scraping": "2024-04-15 20:30:19",
        "url": "https://sport.republika.co.id/berita/sbzeja257/putra-lionel-messi-cetak-lima-gol-untuk-inter-miami"
    },
    {
        "judul": "Mengecat Jalan dan Atap Bisa Turunkan Suhu Kawasan Perkotaan",
        "kategori": "Retizen",
        "waktu_publish": "2 jam yang lalu",
        "waktu_scraping": "2024-04-15 20:30:19",
        "url": "https://retizen.republika.co.id/posts/301431/mengecat-jalan-dan-atap-bisa-turunkan-suhu-kawasan-perkotaan"
    },
    {
        "judul": "Prediksi Ilmuwan Amerika Ini Terbukti, Soal Iran Sampai Imigran Muslim yang Kuasai Barat",
        "kategori": "Khazanah",
        "waktu_publish": "2 jam yang lalu",
        "waktu_scraping": "2024-04-15 20:30:19",
        "url": "https://khazanah.republika.co.id/berita/sbzfc4320/prediksi-ilmuwan-amerika-ini-terbukti-soal-iran-sampai-imigran-muslim-yang-kuasai-barat"
    },
    {
        "judul": "Gol Fahreza Sudin di Menit Akhir, Selamatkan Persita dari Kekalahan",
        "kategori": "Visual",
        "waktu_publish": "2 jam yang lalu",
        "waktu_scraping": "2024-04-15 20:30:19",
        "url": "https://visual.republika.co.id/berita/sbzepc375/gol-fahreza-sudin-di-menit-akhir-selamatkan-persita-dari-kekalahan"
    },
    {
        "judul": "Kemenkes Catat 475 Kematian Akibat DBD Hingga Pekan Ke-15 2024",
        "kategori": "News",
        "waktu_publish": "2 jam yang lalu",
        "waktu_scraping": "2024-04-15 20:30:19",
        "url": "https://news.republika.co.id/berita/sbzf1a409/kemenkes-catat-475-kematian-akibat-dbd-hingga-pekan-ke15-2024"
    },
    {
        "judul": "Drakor Populer dan Seru yang Dibintangi Kim Ji-Won Selain 'Queen of Tears'",
        "kategori": "Ameera",
        "waktu_publish": "2 jam yang lalu",
        "waktu_scraping": "2024-04-15 20:30:19",
        "url": "https://ameera.republika.co.id/berita/sbzerh425/drakor-populer-dan-seru-yang-dibintangi-kim-jiwon-selain-queen-of-tears"
    },
    {
        "judul": "Polres Cianjur Tangkap Dua Perempuan Tersangka TPPO Modus Kawin Kontrak",
        "kategori": "News",
        "waktu_publish": "2 jam yang lalu",
        "waktu_scraping": "2024-04-15 20:30:19",
        "url": "https://news.republika.co.id/berita/sbzer2409/polres-cianjur-tangkap-dua-perempuan-tersangka-tppo-modus-kawin-kontrak"
    }
]